kass_flow/__init__.py
kass_flow/exceptions.py
kass_flow/interfaces.py
kass_flow/kass.py
kass_flow/py.typed
kass_flow-0.2.6.dist-info/WHEEL
kass_flow-0.2.6.dist-info/METADATA
kass_flow-0.2.6.dist-info/RECORD
