Metadata-Version: 2.1
Name: kass-flow
Version: 0.2.6
Summary: Library to manage payments using the KASS API
Home-page: https://github.com/busla/kass-flow
License: MIT
Author: Jón Levy
Author-email: nonni@nonni.cc
Requires-Python: >=3.6,<3.9
Classifier: License :: OSI Approved :: MIT License
Classifier: Programming Language :: Python :: 3
Classifier: Programming Language :: Python :: 3.6
Classifier: Programming Language :: Python :: 3.7
Classifier: Programming Language :: Python :: 3.8
Requires-Dist: requests (>=2.24.0,<3.0.0)
